datarteapi/__init__.py
datarteapi/apiresponse.py
datarteapi/exceptions.py
datarteapi/oauth_manager.py
datarteapi/typing.py
datarteapi/utils.py
datarteapi/clients/__init__.py
datarteapi/clients/balancing_capacity.py
datarteapi/clients/balancing_imbalances_account.py
datarteapi/clients/base_client.py
datarteapi/clients/big_adjusted.py
datarteapi/clients/big_substations.py
datarteapi/clients/big_system.py
datarteapi/clients/ecowatt.py
datarteapi/clients/tariff.py
datarteapi/clients/unavailability_additional_information.py
data_rte_python_api-0.0.1.dist-info/LICENSE
data_rte_python_api-0.0.1.dist-info/METADATA
data_rte_python_api-0.0.1.dist-info/WHEEL
data_rte_python_api-0.0.1.dist-info/top_level.txt
data_rte_python_api-0.0.1.dist-info/RECORD
