Metadata-Version: 2.1
Name: data-rte-python-api
Version: 0.0.1
Summary: Python wrapper for the RTE Data APIs
Home-page: https://github.com/Viicos/data-rte-python-api
Author: Viicos
Author-email: 65306057+Viicos@users.noreply.github.com
Maintainer: Viicos
Maintainer-email: 65306057+Viicos@users.noreply.github.com
License: MIT
Project-URL: Changelog, https://github.com/Viicos/data-rte-python-api/blob/main/CHANGELOG.rst
Keywords: api,rte,datarte
Classifier: Development Status :: 4 - Beta
Classifier: Intended Audience :: Developers
Classifier: Operating System :: OS Independent
Classifier: Programming Language :: Python :: 3
Classifier: Programming Language :: Python :: 3 :: Only
Classifier: Programming Language :: Python :: 3.7
Classifier: Programming Language :: Python :: 3.8
Classifier: Programming Language :: Python :: 3.9
Classifier: Programming Language :: Python :: 3.10
Classifier: Programming Language :: Python :: 3.11
Classifier: Programming Language :: Python :: 3.12
Classifier: Topic :: Internet :: WWW/HTTP
Requires-Python: >=3.7
License-File: LICENSE
Requires-Dist: requests (>=2.14.0)
Requires-Dist: typing-extensions (>=3.10.0.0)
